[

  {
    "ticker": "MSFT",
    "nombre": "Microsoft Corp.",
    "ratio": 30,
    "sector": "Tecnología",
    "descripcion": "Gigante tecnológico enfocado en software, computación en la nube (Azure) e IA."
  },

  {
    "ticker": "AMZN",
    "nombre": "Amazon.com, Inc.",
    "ratio": 144,
    "sector": "Consumo Cíclico",
    "descripcion": "Líder global en comercio electrónico, logística y servicios en la nube (AWS)."
  },
  
  {
    "ticker": "NVDA",
    "nombre": "NVIDIA Corp.",
    "ratio": 48,
    "sector": "Semiconductores",
    "descripcion": "Líder absoluto en unidades de procesamiento gráfico (GPU) e infraestructura para Inteligencia Artificial."
  },
  
  {
    "ticker": "GOOGL",
    "nombre": "Alphabet Inc.",
    "ratio": 58,
    "sector": "Tecnología",
    "descripcion": "Matriz de Google, líder en búsquedas web, publicidad digital, YouTube e Inteligencia Artificial."
  },
  
  {
    "ticker": "META",
    "nombre": "Meta Platforms, Inc.",
    "ratio": 24,
    "sector": "Tecnología",
    "descripcion": "Propietaria de Facebook, Instagram, WhatsApp y pionera en el desarrollo del Metaverso."
  },
  
  {
    "ticker": "NFLX",
    "nombre": "Netflix, Inc.",
    "ratio": 16,
    "sector": "Entretenimiento",
    "descripcion": "El servicio de streaming de entretenimiento por suscripción líder en el mundo."
  },
  
  {
    "ticker": "IBIT",
    "nombre": "iShares Bitcoin Trust",
    "ratio": 10,
    "sector": "ETF",
    "descripcion": "ETF spot que replica el precio del Bitcoin (BTC) en el mercado institucional."
  },
  {
    "ticker": "AMAT",
    "nombre": "Applied Matterials",
    "ratio": 5,
    "sector": "VER",
    "descripcion": "completar"
  },
   {
    "ticker": "ASML",
    "nombre": "ASML Holding NV",
    "ratio": 5,
    "sector": "VER",
    "descripcion": "completar"
  },
   {
    "ticker": "LRCX",
    "nombre": "Lam Research corp.",
    "ratio": 5,
    "sector": "VER",
    "descripcion": "completar"
  },
   {
    "ticker": "ORLY",
    "nombre": "Oreilly Automotive",
    "ratio": 5,
    "sector": "VER",
    "descripcion": "completar"
  },
   {
    "ticker": "V",
    "nombre": "Visa Inc.",
    "ratio": 5,
    "sector": "VER",
    "descripcion": "completar"
  }
]
