[
  {
    "ticker": "YM39O",
    "nombre": "YPF S.A. Clase XXXIX",
    "ratio": 1,
    "sector": "Obligación Negociable",
    "descripcion": "ON de YPF S.A. en dólares bajo Ley Nueva York (regulación S), vencimiento en 2031 con cupón del 9.00% anual."
  },
  {
    "ticker": "YFCLO",
    "nombre": "YPF S.A. Clase XVI",
    "ratio": 1,
    "sector": "Obligación Negociable",
    "descripcion": "ON de YPF S.A. en dólares, vencimiento en 2026 con un cupón del 9.00% anual y amortización al vencimiento."
  },
  {
    "ticker": "YM34O",
    "nombre": "YPF S.A. Clase XXXIV",
    "ratio": 1,
    "sector": "Obligación Negociable",
    "descripcion": "ON de YPF S.A. emitida en dólares, con vencimiento final en 2026 y cupón del 9.00% anual."
  },
  {
    "ticker": "YMCJO",
    "nombre": "YPF S.A. Clase CXXV",
    "ratio": 1,
    "sector": "Obligación Negociable",
    "descripcion": "ON de YPF S.A. en dólares billete, vencimiento en 2026 con una tasa de interés del 9.00% nominal anual."
  },
  {
    "ticker": "CS48O",
    "nombre": "Cresud S.A.C.I.F. y A. Clase XLVIII",
    "ratio": 1,
    "sector": "Obligación Negociable",
    "descripcion": "ON de Cresud emitida en dólares, vencimiento en 2028 con cupón del 8.50% anual y pagos semestrales de interés."
  },
  {
    "ticker": "IRCPO",
    "nombre": "IRSA Inversiones y Representaciones S.A. Clase XIV",
    "ratio": 1,
    "sector": "Obligación Negociable",
    "descripcion": "ON de IRSA (también identificada como IRC1O), vencimiento en 2028 con cupón del 8.75% anual en dólares."
  },
  {
    "ticker": "MSSEO",
    "nombre": "MSU Energy S.A. Clase V",
    "ratio": 1,
    "sector": "Obligación Negociable",
    "descripcion": "ON de MSU Energy dedicada a la generación térmica, vencimiento en 2025 con cupón del 7.35% anual en dólares."
  },
  {
    "ticker": "GN49O",
    "nombre": "Genneia S.A. Clase XLIX",
    "ratio": 1,
    "sector": "Obligación Negociable",
    "descripcion": "ON Verde de Genneia bajo Ley Nueva York, enfocada en energías renovables, vencimiento en 2027 con cupón del 8.50% anual."
  },
  {
    "ticker": "TSC4O",
    "nombre": "Transportadora de Gas del Sur S.A. Clase IV",
    "ratio": 1,
    "sector": "Obligación Negociable",
    "descripcion": "ON de TGS en dólares, vencimiento en 2025 con cupón del 6.75% anual y pagos semestrales de interés."
  },
  {
    "ticker": "RUCDO",
    "nombre": "MSU Energy S.A. Clase VIII",
    "ratio": 1,
    "sector": "Obligación Negociable",
    "descripcion": "ON de MSU Energy en dólares, con vencimiento en 2026 y cupón del 7.75% anual pagadero semestralmente."
  },
  {
    "ticker": "PECNO",
    "nombre": "Pampa Energía S.A. Clase M",
    "ratio": 1,
    "sector": "Obligación Negociable",
    "descripcion": "ON de Pampa Energía emitida en dólares bajo Ley Local, vencimiento en 2026 con cupón del 9.50% anual."
  },
  {
    "ticker": "PQCSO",
    "nombre": "Pampa Energía S.A. Clase IX",
    "ratio": 1,
    "sector": "Obligación Negociable",
    "descripcion": "ON de Pampa Energía en dólares bajo Ley Nueva York, con vencimiento en 2027 y tasa de interés fija del 9.125% anual."
  }
]